googledrivedownloader/__init__.py
googledrivedownloader/download.py
googledrivedownloader-1.0.0.dist-info/METADATA
googledrivedownloader-1.0.0.dist-info/WHEEL
googledrivedownloader-1.0.0.dist-info/licenses/LICENSE
googledrivedownloader-1.0.0.dist-info/RECORD
