Metadata-Version: 2.4
Name: googledrivedownloader
Version: 1.0.0
Summary: Minimal class to download shared files from Google Drive.
Project-URL: Homepage, https://github.com/ndrplz/google-drive-downloader
Project-URL: Issues, https://github.com/ndrplz/google-drive-downloader/issues
Author: Davide Abati and Andrea Palazzi
Maintainer-email: Andrea Palazzi <ndrplz@gmail.com>
License-File: LICENSE
Requires-Python: >=3.8
Requires-Dist: requests
